{"arch_arch.md":"DEV3BWX_","index.md":"BeLl4wXQ","java_base_javabase.md":"CFG155Ac","java_collection_javajihe.md":"BzKf0_z1","java_object_javaobject.md":"MN6zysC9","java_special_javaapi.md":"0hVJ6Ai7","price_01-terminology_index.md":"C-lbkbeq","price_02-chart-basics_02a.md":"CiLFcSkp","price_02-chart-basics_02b.md":"BsUL34KS","price_02-chart-basics_02c.md":"2NB0nhb7","price_02-chart-basics_02d.md":"CHZf1B6n","price_03-forex-basics_03a.md":"D04BhD-o","price_03-forex-basics_03b.md":"dJb43kZQ","price_03-forex-basics_03c.md":"DD6hNrvH","price_03-forex-basics_03d.md":"CQzHbntG","price_03-forex-basics_03e.md":"fqaVq6Fs","price_04-my-setup_index.md":"BhNJYQ6L","price_05-program-trading_index.md":"CKRklRK4","price_06-personality-traits_index.md":"DyqYSXa5","price_07-starting-out_07a.md":"TjOTbMNj","price_07-starting-out_07b.md":"DU8mh9cd","price_08-candles-setups_08a.md":"C7p3gAcR","price_08-candles-setups_08b.md":"DL1laoVT","price_08-candles-setups_08c.md":"DAoaWKco","price_08-candles-setups_08d.md":"Dd7iXW_C","price_09-pullbacks-counting_09a.md":"C5XwrUUZ","price_09-pullbacks-counting_09b.md":"Btq1xKxu","price_09-pullbacks-counting_09c.md":"CLl5fbL2","price_10-buying-selling-pressure_10a.md":"DFhjRF-1","price_10-buying-selling-pressure_10b.md":"CdE_lAw1","price_11-gaps_11a.md":"DXF_-7BE","price_11-gaps_11b.md":"B8mbOhN4","price_11-gaps_11c.md":"BiM_Em8X","price_11-gaps_11d.md":"CIlokrpM","price_12-market-cycle_12a.md":"Dz22BJKI","price_12-market-cycle_12b.md":"kWbU32Jt","price_12-market-cycle_12c.md":"DpYfZWGz","price_13-always-in_13a.md":"D6rXTwvM","price_13-always-in_13b.md":"D8WuT1d5","price_13-always-in_13c.md":"D-h8XQf0","price_14-trends_14a.md":"DkuB0QCJ","price_14-trends_14b.md":"D1I4vYNQ","price_14-trends_14c.md":"DALd49JV","price_14-trends_14d.md":"otoB3cYj","price_14-trends_14e.md":"Bq6LaO7d","price_15-breakouts_15a.md":"C5tpGW71","price_15-breakouts_15b.md":"D-yNtXZa","price_15-breakouts_15c.md":"D-uMlkmr","price_15-breakouts_15d.md":"CcGXCZL2","price_15-breakouts_15e.md":"Ce3-NNdJ","price_15-breakouts_15f.md":"b-LezWmo","price_15-breakouts_15g.md":"Bgp6G7rr","price_15-breakouts_15h.md":"BP9mxxJ2","price_16-channels_16a.md":"BkKmFuBU","price_16-channels_16b.md":"DS7FAfd_","price_16-channels_16c.md":"DhPiEmyW","price_16-channels_16d.md":"BN7avtUe","price_16-channels_16e.md":"lu49r4fi","price_16-channels_16f.md":"B09lmvAL","price_17-tight-channels_17a.md":"D5nsT-Ul","price_17-tight-channels_17b.md":"BfcdJBJR","price_18-trading-ranges_18a.md":"Czo3rJin","price_18-trading-ranges_18b.md":"C24e_gD-","price_18-trading-ranges_18c.md":"Tch55X4Q","price_18-trading-ranges_18d.md":"BcboEH5E","price_18-trading-ranges_18e.md":"BseYKVoN","price_18-trading-ranges_18f.md":"D-3vZSz1","price_19-support-resistance_19a.md":"C9DggtqM","price_19-support-resistance_19b.md":"B-aIUabx","price_19-support-resistance_19c.md":"Ba20ZHQ8","price_19-support-resistance_19d.md":"DYllfXZf","price_19-support-resistance_19e.md":"UghXd8F2","price_20-measured-moves_20a.md":"CctMjIQE","price_20-measured-moves_20b.md":"CWdtGlZd","price_21-reversals_21a.md":"CAiAgjWg","price_21-reversals_21b.md":"Be-PQfN1","price_21-reversals_21c.md":"cdmP6gk5","price_21-reversals_21d.md":"Cv5_S51e","price_22-major-trend-reversals_22a.md":"BhOXuYjl","price_22-major-trend-reversals_22b.md":"CyvYIX_O","price_22-major-trend-reversals_22c.md":"zA_GIStZ","price_22-major-trend-reversals_22d.md":"HCuw8eUH","price_23-final-flags_23a.md":"DXKZ2y4U","price_23-final-flags_23b.md":"z1IM5Brp","price_24-wedges_24a.md":"DORPpJBn","price_24-wedges_24b.md":"Dx3245s9","price_24-wedges_24c.md":"BAuwvgHC","price_24-wedges_24d.md":"DURWMUQF","price_24-wedges_24e.md":"HXD4OM8T","price_25-double-tops-bottoms_25a.md":"DlR6nGVi","price_25-double-tops-bottoms_25b.md":"BMnb-aOr","price_26-triangles_26a.md":"D7xkV4D3","price_26-triangles_26b.md":"DfNVqNUU","price_27-head-shoulders_27a.md":"CusBXqeY","price_27-head-shoulders_27b.md":"FRSZFzEm","price_28-rounded-tops-bottoms_index.md":"Dsj4mOPz","price_29-climaxes_29a.md":"Bidv7g69","price_29-climaxes_29b.md":"D4UbLIF9","price_29-climaxes_29c.md":"CY-24ZyB","price_29-climaxes_29d.md":"BWFR3vXX","price_29-climaxes_29e.md":"zziYStyf","price_30-trading-setups_30a.md":"f_RViqrY","price_30-trading-setups_30b.md":"D3U6wumu","price_30-trading-setups_30c.md":"Cw3vtwNm","price_30-trading-setups_30d.md":"C2CmQQSY","price_30-trading-setups_30e.md":"ByjibkzG","price_31-trading-entries_31a.md":"Ck6rMBUS","price_31-trading-entries_31b.md":"CSOdYnDt","price_31-trading-entries_31c.md":"ClthsBBG","price_31-trading-entries_31d.md":"CGX_4jAs","price_32-trading-exits_32a.md":"BED9_YUq","price_32-trading-exits_32b.md":"dg3kvFHX","price_32-trading-exits_32c.md":"DNO1LCpT","price_33-protective-stops_33a.md":"BlQU2hmy","price_33-protective-stops_33b.md":"C30Lzdqg","price_33-protective-stops_33c.md":"B9Sp84BO","price_33-protective-stops_33d.md":"CLQW9YTO","price_33-protective-stops_33e.md":"BIXBCkdq","price_33-protective-stops_33f.md":"DxDfnA8y","price_33-protective-stops_33g.md":"DbJyC-kb","price_34-actual-risk_34a.md":"CXpZWkcI","price_34-actual-risk_34b.md":"1Xe4x4NL","price_35-scaling-in_35a.md":"DIl-681X","price_35-scaling-in_35b.md":"BN5PE6Z9","price_35-scaling-in_35c.md":"CDAgA5zt","price_36-trade-management_36a.md":"BRaVkJWR","price_36-trade-management_36b.md":"96lKSaSa","price_mes-recap_20250307.md":"DuRCbtNW","price_mes-recap_20250310.md":"DLXnz0Z2","price_mes-recap_20250311.md":"DFh2dI2Q","price_mes-recap_20250312.md":"DN_GiBqr","price_mes-recap_20250313.md":"D5RyVIHE","price_mes-recap_20250314.md":"BNn1a2Oq","price_mes-recap_20250317.md":"C7dyrK4f","price_mes-recap_20250318.md":"DzkiWxZK","price_mes-recap_20250319.md":"CNODdBRp","price_mes-recap_20250320.md":"B0CLCNSU","price_mes-recap_20250321.md":"D1_T0g7s","price_mes-recap_20250409.md":"CZhx4Mhy","price_mes-recap_20250410.md":"YAVqJZIJ","price_mes-recap_20250411.md":"5_LlbmUf","price_price-action-all-in-one_index.md":"KflUjoRj","price_qa-summary_about-liquidity-grab.md":"CaYgxKVp","yx.md":"9jX_rb_V"}
